lilo/__init__.py
lilo/__main__.py
lilo/integrate.py
lilo/markov.py
lilo/modal.py
lilo/numerics.py
lilo/realize.py
lilo/spec.py
lilo/system.py
lilo/validation.py
lilo/archive/ExtractModes.py
lilo/archive/okid.py
lilo/archive/realization.py
lilo/archive/srim.py
lilo/brace2/__main__.py
lilo/utilities/__init__.py
lilo/utilities/config.py
lilo/utilities/printing.py
lilo/utilities/testing.py
peer_lilo-0.0.1.dist-info/METADATA
peer_lilo-0.0.1.dist-info/WHEEL
peer_lilo-0.0.1.dist-info/entry_points.txt
peer_lilo-0.0.1.dist-info/top_level.txt
peer_lilo-0.0.1.dist-info/RECORD
