Metadata-Version: 2.1
Name: peer-lilo
Version: 0.0.1
Summary: Fast and friendly system identification for structures.
Author-email: Chrystal Chern <52893467+chrystalchern@users.noreply.github.com>
Project-URL: repository, http://github.com/BRACE2/lilo
Project-URL: documentation, https://brace2.github.io/lilo
Keywords: seismic,earthquake
Classifier: Development Status :: 4 - Beta
Classifier: Intended Audience :: Science/Research
Classifier: Intended Audience :: Developers
Classifier: License :: OSI Approved :: BSD License
Classifier: Programming Language :: C
Classifier: Programming Language :: Python
Classifier: Programming Language :: Python :: 3
Classifier: Programming Language :: Python :: 3.7
Classifier: Programming Language :: Python :: 3.8
Classifier: Programming Language :: Python :: 3.9
Classifier: Programming Language :: Python :: 3.10
Classifier: Programming Language :: Python :: 3.11
Classifier: Programming Language :: Python :: 3.12
Classifier: Programming Language :: Python :: 3 :: Only
Classifier: Programming Language :: Python :: Implementation :: CPython
Classifier: Topic :: Software Development
Classifier: Topic :: Scientific/Engineering
Classifier: Operating System :: Microsoft :: Windows
Classifier: Operating System :: POSIX
Classifier: Operating System :: Unix
Classifier: Operating System :: MacOS
Requires-Dist: numpy
Requires-Dist: scipy
Requires-Dist: tqdm
Requires-Dist: quakeio
Requires-Dist: matplotlib
Requires-Dist: plotly
Requires-Dist: pandas
Requires-Dist: control
Requires-Dist: sdof
Requires-Dist: opensees
